{
   "density" : 0.40,
   "dimension_filter" : [ "dimension_id:52" ],
   "filler" : {
      "type" : "layered",
      "values" : [
         {
            "primary" : "ore:tetrahedrite"
         },
         {
            "secondary" : "ore:tetrahedrite"
         },
         {
            "between" : "ore:copper"
         },
         {
            "sporadic" : "ore:stibnite"
         }
      ]
   },
   "generator" : {
      "radius" : [ 17, 24 ],
      "type" : "layered"
   },
   "max_height" : 40,
   "min_height" : 0,
   "name" : "Mars Tetrahedrite",
   "vein_populator" : {
      "material" : "banded_iron",
      "type" : "surface_rock"
   },
   "weight" : 60
}