{
  "catalystStack": {
    "registryName": {
      "domain": "gregtech",
      "path": "machine"
    },
    "meta": 147
  },
  "components": [
    {
      "weight": 60,
      "oreName": "oreCalcite"
    },
    {
      "weight": 20,
      "oreName": "oreSoapstone"
    },
    {
      "weight": 60,
      "oreName": "oreVanadiumMagnetite"
    },
    {
      "weight": 50,
      "oreName": "oreSalt"
    },
    {
      "weight": 50,
      "oreName": "oreRockSalt"
    },
    {
      "weight": 50,
      "oreName": "oreSphalerite"
    },
    {
      "weight": 5,
      "oreName": "oreIron"
    },
    {
      "weight": 15,
      "oreName": "oreNickel"
    },
    {
      "weight": 200,
      "oreName": "oreCopper"
    },
    {
      "weight": 20,
      "oreName": "oreTin"
    },
    {
      "weight": 40,
      "oreName": "oreLead"
    },
    {
      "weight": 50,
      "oreName": "oreSilver"
    },
    {
      "weight": 50,
      "oreName": "oreGold"
    },
    {
      "weight": 70,
      "oreName": "oreCassiterite"
    }
  ],
  "explosionStrength": 10.0,
  "radius": 16,
  "maxWeight": 1040,
  "version": 4,
  "cost": 300000
}