{
   "density" : 0.50,
   "dimension_filter" : [ "dimension_id:20" ],
   "filler" : {
      "type" : "layered",
      "values" : [
         {
            "primary" : "ore:lazurite"
         },
         {
            "secondary" : "ore:sodalite"
         },
         {
            "between" : "ore:lapis"
         },
         {
            "sporadic" : "ore:calcite"
         }
      ]
   },
   "generation_predicate" : [ "ore_dict:cobblestone" ],
   "generator" : {
      "radius" : [ 8, 20 ],
      "type" : "layered"
   },
   "max_height" : 100,
   "min_height" : 40,
   "name" : "Betweenland Lapis",
   "vein_populator" : {
      "material" : "lapis",
      "type" : "surface_rock"
   },
   "weight" : 40
}